iqoapi/__init__.py
iqoapi/api.py
iqoapi/constants.py
iqoapi/expiration.py
iqoapi/global_value.py
iqoapi/stable_api.py
iqoapi/http/__init__.py
iqoapi/http/appinit.py
iqoapi/http/auth.py
iqoapi/http/billing.py
iqoapi/http/buyback.py
iqoapi/http/changebalance.py
iqoapi/http/getprofile.py
iqoapi/http/getregdata.py
iqoapi/http/login.py
iqoapi/http/loginv2.py
iqoapi/http/profile.py
iqoapi/http/register.py
iqoapi/http/resource.py
iqoapi/http/token.py
iqoapi/ws/__init__.py
iqoapi/ws/client.py
iqoapi/ws/chanels/__init__.py
iqoapi/ws/chanels/api_game_betinfo.py
iqoapi/ws/chanels/api_game_getoptions.py
iqoapi/ws/chanels/base.py
iqoapi/ws/chanels/buy_place_order_temp.py
iqoapi/ws/chanels/buyback.py
iqoapi/ws/chanels/buyv2.py
iqoapi/ws/chanels/buyv3.py
iqoapi/ws/chanels/cancel_order.py
iqoapi/ws/chanels/candles.py
iqoapi/ws/chanels/change_auto_margin_call.py
iqoapi/ws/chanels/change_tpsl.py
iqoapi/ws/chanels/changebalance.py
iqoapi/ws/chanels/close_position.py
iqoapi/ws/chanels/digital_option.py
iqoapi/ws/chanels/get_available_leverages.py
iqoapi/ws/chanels/get_deferred_orders.py
iqoapi/ws/chanels/get_financial_information.py
iqoapi/ws/chanels/get_order.py
iqoapi/ws/chanels/get_overnight_fee.py
iqoapi/ws/chanels/get_positions.py
iqoapi/ws/chanels/heartbeat.py
iqoapi/ws/chanels/instruments.py
iqoapi/ws/chanels/sell_option.py
iqoapi/ws/chanels/setactives.py
iqoapi/ws/chanels/ssid.py
iqoapi/ws/chanels/strike_list.py
iqoapi/ws/chanels/subscribe.py
iqoapi/ws/chanels/traders_mood.py
iqoapi/ws/chanels/unsubscribe.py
iqoapi/ws/objects/__init__.py
iqoapi/ws/objects/base.py
iqoapi/ws/objects/betinfo.py
iqoapi/ws/objects/candles.py
iqoapi/ws/objects/listinfodata.py
iqoapi/ws/objects/profile.py
iqoapi/ws/objects/timesync.py
iqoapi-0.1.dist-info/METADATA
iqoapi-0.1.dist-info/WHEEL
iqoapi-0.1.dist-info/top_level.txt
iqoapi-0.1.dist-info/RECORD
